setup.py
airscooter_urban_physiology_plugin/cli.py
airscooter_urban_physiology_plugin.egg-info/PKG-INFO
airscooter_urban_physiology_plugin.egg-info/SOURCES.txt
airscooter_urban_physiology_plugin.egg-info/dependency_links.txt
airscooter_urban_physiology_plugin.egg-info/entry_points.txt
airscooter_urban_physiology_plugin.egg-info/requires.txt
airscooter_urban_physiology_plugin.egg-info/top_level.txt