Metadata-Version: 1.1
Name: airscooter-urban-physiology-plugin
Version: 0.0.1
Summary: Plugin bringing the Urban Physiology workflow to airscooter.
Home-page: https://github.com/ResidentMario/airscooter-urban-physiology-plugin
Author: Aleksey Bilogur
Author-email: aleksey.bilogur@gmail.com
License: UNKNOWN
Download-URL: https://github.com/ResidentMario/airscooter-urban-physiology-plugin/tarball/0.0.1
Keywords: data,data analysis,open data
Platform: UNKNOWN
